gestor_ventas/__init__.py
gestor_ventas/descuentos.py
gestor_ventas/exceptions.py
gestor_ventas/gestor_ventas.py
gestor_ventas/impuestos.py
gestor_ventas/precios.py
tests/__init__.py
tests/test_gestor_ventas.py
gestor_ventas-0.1.0.dist-info/LICENSE
gestor_ventas-0.1.0.dist-info/METADATA
gestor_ventas-0.1.0.dist-info/WHEEL
gestor_ventas-0.1.0.dist-info/top_level.txt
gestor_ventas-0.1.0.dist-info/RECORD
